<?xml version="1.0" encoding="UTF-8"?>
<Defs>
  <Personality.PersonalityNodeDef>
    <defName>Rationality</defName>
    <highDescription>{PAWN_nameDef} is more likely to think things through than make emotional decisions. On the other hand, {PAWN_pronoun} is less in tune with {PAWN_possessive} emotions and may struggle to articulate them.</highDescription>
    <lowDescription>{PAWN_nameDef} works on vibes. {PAWN_pronoun}'s worse at things requiring logical thought, but handles {PAWN_possessive} emotions better and has a better read on people.</lowDescription>
    <highLabel>rational</highLabel>
    <lowLabel>emotional</lowLabel>
    <traitModifiers>
      <li>
        <trait>TooSmart</trait>
        <modifier>0.5</modifier>
      </li>
      <li MayRequire="vanillaexpanded.vanillatraitsexpanded">
        <trait>VTE_Academian</trait>
        <modifier>0.05</modifier>
      </li>
    </traitModifiers>
    <statModifiers>
      <li>
        <statDef>ResearchSpeedFactor</statDef>
        <isFactor>true</isFactor>
        <value>1.1</value>
        <beginsAt>0.25</beginsAt>
        <maxValueAt>1</maxValueAt>
      </li>
      <li>
        <statDef>MentalBreakThreshold</statDef>
        <isFactor>false</isFactor>
        <value>-0.1</value>
        <beginsAt>0.25</beginsAt>
      </li>
      <li>
        <statDef>MentalBreakThreshold</statDef>
        <isFactor>false</isFactor>
        <value>0.05</value>
        <beginsAt>-0.5</beginsAt>
      </li>
      <li>
        <statDef>NegotiationAbility</statDef>
        <isFactor>false</isFactor>
        <value>0.05</value>
        <beginsAt>-0.25</beginsAt>
      </li>
    </statModifiers>
  </Personality.PersonalityNodeDef>
  <Personality.PersonalityNodeDef>
    <defName>Assertiveness</defName>
    <highDescription>{PAWN_nameDef} gives voice to their needs and opinions.</highDescription>
    <lowDescription>{PAWN_nameDef} feels uncomfortable sticking up for themselves.</lowDescription>
    <highLabel>outspoken</highLabel>
    <lowLabel>meek</lowLabel>
    <traitModifiers>
      <li MayRequire="vanillaexpanded.vanillatraitsexpanded">
        <trait>VTE_Brave</trait>
        <modifier>0.3</modifier>
      </li>
      <li MayRequire="vanillaexpanded.vanillatraitsexpanded">
        <trait>VTE_Coward</trait>
        <modifier>-0.3</modifier>
      </li>
      <li>
        <trait>Wimp</trait>
        <modifier>-0.25</modifier>
      </li>
    </traitModifiers>
    <statModifiers>
      <li>
        <statDef>TradePriceImprovement</statDef>
        <isFactor>true</isFactor>
        <value>1.1</value>
        <beginsAt>0.25</beginsAt>
      </li>
    </statModifiers>
  </Personality.PersonalityNodeDef>
  <Personality.PersonalityNodeDef>
    <defName>Compassion</defName>
    <highDescription>{PAWN_nameDef} is in tune with the emotions of others. {PAWN_pronoun} prioritizes kindness and helping others.</highDescription>
    <lowDescription>{PAWN_nameDef}'s first priority is {PAWN_possessive} own wellbeing. {PAWN_pronoun} will not go out of their way to help someone.</lowDescription>
    <highLabel>empathetic</highLabel>
    <lowLabel>ruthless</lowLabel>
    <traitModifiers>
      <li>
        <trait>Psychopath</trait>
        <modifier>-5</modifier>
      </li>
      <li>
        <trait>Kind</trait>
        <modifier>1.5</modifier>
      </li>
      <li>
        <trait>Bloodlust</trait>
        <modifier>-0.5</modifier>
      </li>
      <li>
        <trait>Greedy</trait>
        <modifier>-0.1</modifier>
      </li>
      <li>
        <trait>Jealous</trait>
        <modifier>-0.1</modifier>
      </li>
      <li>
        <trait>DislikesMen</trait>
        <modifier>-0.25</modifier>
      </li>
      <li>
        <trait>DislikesWomen</trait>
        <modifier>-0.25</modifier>
      </li>
    </traitModifiers>
    <preceptModifiers>
      <li>
        <preceptDef>Execution_Abhorrent</preceptDef>
        <modifier>0.15</modifier>
      </li>
      <li>
        <preceptDef>Execution_Horrible</preceptDef>
        <modifier>.07</modifier>
      </li>
      <li>
        <preceptDef>Execution_DontCare</preceptDef>
        <modifier>-0.04</modifier>
      </li>
      <li>
        <preceptDef>Execution_RespectedIfGuilty</preceptDef>
        <modifier>-0.08</modifier>
      </li>
      <li>
        <preceptDef>Execution_Required</preceptDef>
        <modifier>-0.15</modifier>
      </li>
      <li>
        <preceptDef>AnimalConnection_Strong</preceptDef>
        <modifier>0.07</modifier>
      </li>
      <li>
        <preceptDef>Bonding_Disapproved</preceptDef>
        <modifier>-0.07</modifier>
      </li>
    </preceptModifiers>
    <statModifiers>
      <li>
        <statDef>TameAnimalChance</statDef>
        <beginsAt>0.25</beginsAt>
        <isFactor>true</isFactor>
        <value>1.1</value>
      </li>
      <li>
        <statDef>ArrestSuccessChance</statDef>
        <beginsAt>-0.25</beginsAt>
        <isFactor>true</isFactor>
        <value>1.1</value>
      </li>
      <li>
        <statDef>SuppressionPower</statDef>
        <beginsAt>-0.25</beginsAt>
        <isFactor>false</isFactor>
        <value>0.05</value>
      </li>
    </statModifiers>
  </Personality.PersonalityNodeDef>
  <Personality.PersonalityNodeDef>
    <defName>Ambition</defName>
    <highDescription>{PAWN_nameDef} has a strong internal motivation to improve {PAWN_objective}self and {PAWN_possessive} colony.</highDescription>
    <lowDescription>{PAWN_nameDef} is happy with how things are, and doesn't have much motivation to change it.</lowDescription>
    <highLabel>driven</highLabel>
    <lowLabel>complacent</lowLabel>
    <traitModifiers>
      <li MayRequire="vanillaexpanded.vanillatraitsexpanded">
        <trait>VTE_Workaholic</trait>
        <modifier>0.5</modifier>
      </li>
      <li MayRequire="vanillaexpanded.vanillatraitsexpanded">
        <trait>VTE_Rebel</trait>
        <modifier>-0.1</modifier>
      </li>
      <li MayRequire="vanillaexpanded.vanillatraitsexpanded">
        <trait>VTE_Submissive</trait>
        <modifier>-0.2</modifier>
      </li>
      <li MayRequire="vanillaexpanded.vanillatraitsexpanded">
        <trait>VTE_Vengeful</trait>
        <modifier>0.25</modifier>
      </li>
      <li MayRequire="vanillaexpanded.vanillatraitsexpanded">
        <trait>VTE_Snob</trait>
        <modifier>0.4</modifier>
      </li>
    </traitModifiers>
    <preceptModifiers>
      <li>
        <preceptDef>Raiding_Respected</preceptDef>
        <modifier>0.15</modifier>
      </li>
      <li>
        <preceptDef>Raiding_Required</preceptDef>
        <modifier>0.3</modifier>
      </li>
      <li>
        <preceptDef>Proselytizing_Occasionally</preceptDef>
        <modifier>0.08</modifier>
      </li>
      <li>
        <preceptDef>Proselytizing_Frequently</preceptDef>
        <modifier>0.15</modifier>
      </li>
    </preceptModifiers>
    <statModifiers>
      <li>
        <statDef>WorkSpeedGlobal</statDef>
        <isFactor>false</isFactor>
        <beginsAt>0.5</beginsAt>
        <value>.05</value>
      </li>
    </statModifiers>
  </Personality.PersonalityNodeDef>
  <Personality.PersonalityNodeDef>
    <defName>Meticulousness</defName>
    <highDescription>{PAWN_nameDef} is thorough in everything they do. Unfortunately, they put a lot of stress on themselves because of this.</highDescription>
    <lowDescription>{PAWN_nameDef} cuts corners. {PAWN_possessive} work is generally a bit lower quality, but {PAWN_pronoun} doesn't get stressed out over it.</lowDescription>
    <highLabel>meticulous</highLabel>
    <lowLabel>careless</lowLabel>
    <traitModifiers>
      <li>
        <trait>Industriousness</trait>
        <degree>-1</degree>
        <modifier>-1</modifier>
      </li>
      <li>
        <trait>Industriousness</trait>
        <degree>1</degree>
        <modifier>0.25</modifier>
      </li>
      <li>
        <trait>Industriousness</trait>
        <degree>2</degree>
        <modifier>0.5</modifier>
      </li>
      <li MayRequire="vanillaexpanded.vanillatraitsexpanded">
        <trait>VTE_Perfectionist</trait>
        <modifier>1</modifier>
      </li>
      <li MayRequire="vanillaexpanded.vanillatraitsexpanded">
        <trait>VTE_Neat</trait>
        <modifier>0.15</modifier>
      </li>
      <li MayRequire="vanillaexpanded.vanillatraitsexpanded">
        <trait>VTE_Slob</trait>
        <modifier>-0.15</modifier>
      </li>
    </traitModifiers>
    <statModifiers>
      <li>
        <statDef>MentalBreakThreshold</statDef>
        <isFactor>false</isFactor>
        <beginsAt>0.25</beginsAt>
        <value>0.15</value>
      </li>
      <li>
        <statDef>MentalBreakThreshold</statDef>
        <isFactor>false</isFactor>
        <beginsAt>-0.25</beginsAt>
        <value>-0.15</value>
      </li>
    </statModifiers>
  </Personality.PersonalityNodeDef>
  <Personality.PersonalityNodeDef MayRequire="Ludeon.RimWorld.Ideology">
    <defName>Lawfulness</defName>
    <highDescription>{PAWN_nameDef} cares a lot about rules. {PAWN_pronoun} is very unlikely to break the precepts of {PAWN_possessive} ideoligion.</highDescription>
    <lowDescription>{PAWN_nameDef} does what seems right in the moment. {PAWN_pronoun} may break the precepts of {PAWN_possessive} ideoligion if it feels appropriate.</lowDescription>
    <lowLabel>chaotic</lowLabel>
    <highLabel>lawful</highLabel>
    <preceptModifiers>
      <li>
        <preceptDef>IdeoDiversity_Approved</preceptDef>
        <modifier>-0.15</modifier>
      </li>
      <li>
        <preceptDef>IdeoDiversity_Exalted</preceptDef>
        <modifier>-0.25</modifier>
      </li>
      <li>
        <preceptDef>IdeoDiversity_Respected</preceptDef>
        <modifier>-0.075</modifier>
      </li>
      <li>
        <preceptDef>IdeoDiversity_Standard</preceptDef>
        <modifier>0</modifier>
      </li>
      <li>
        <preceptDef>IdeoDiversity_Disapproved</preceptDef>
        <modifier>0.075</modifier>
      </li>
      <li>
        <preceptDef>IdeoDiversity_Horrible</preceptDef>
        <modifier>0.15</modifier>
      </li>
      <li>
        <preceptDef>IdeoDiversity_Abhorrent</preceptDef>
        <modifier>0.25</modifier>
      </li>
    </preceptModifiers>
  </Personality.PersonalityNodeDef>
</Defs>